LICENSE
MANIFEST.in
README.rst
requirements.txt
setup.cfg
setup.py
concreate/__init__.py
concreate/builder.py
concreate/cli.py
concreate/errors.py
concreate/generator.py
concreate/log.py
concreate/module.py
concreate/template_helper.py
concreate/tools.py
concreate/version.py
concreate.egg-info/PKG-INFO
concreate.egg-info/SOURCES.txt
concreate.egg-info/dependency_links.txt
concreate.egg-info/entry_points.txt
concreate.egg-info/requires.txt
concreate.egg-info/top_level.txt
concreate/builders/__init__.py
concreate/builders/docker.py
concreate/builders/osbs.py
concreate/descriptor/__init__.py
concreate/descriptor/base.py
concreate/descriptor/env.py
concreate/descriptor/execute.py
concreate/descriptor/image.py
concreate/descriptor/label.py
concreate/descriptor/module.py
concreate/descriptor/modules.py
concreate/descriptor/osbs.py
concreate/descriptor/overrides.py
concreate/descriptor/packages.py
concreate/descriptor/port.py
concreate/descriptor/repository.py
concreate/descriptor/resource.py
concreate/descriptor/run.py
concreate/descriptor/volume.py
concreate/templates/__init__.py
concreate/templates/template.jinja
concreate/test/__init__.py
concreate/test/collector.py
concreate/test/runner.py