Metadata-Version: 1.1
Name: concreate
Version: 1.4.1
Summary: Containers creator
Home-page: https://github.com/concrt/concreate
Author: Cloud Enablement
Author-email: cloud-enablement-feedback@redhat.com
License: MIT
Download-URL: https://github.com/concrt/concreate/archive/1.4.1.tar.gz
Keywords: docker
Platform: UNKNOWN
